librarysystem533/main.py
librarysystem533/admin/__init__.py
librarysystem533/admin/admin_action.py
librarysystem533/admin/book_management_system.py
librarysystem533/admin/user_management_system.py
librarysystem533/user/__init__.py
librarysystem533/user/account_system.py
librarysystem533/user/book_system.py
librarysystem533/user/user_action.py
librarysystem533-0.0.1.dist-info/LICENSE.txt
librarysystem533-0.0.1.dist-info/METADATA
librarysystem533-0.0.1.dist-info/WHEEL
librarysystem533-0.0.1.dist-info/top_level.txt
librarysystem533-0.0.1.dist-info/RECORD
