Metadata-Version: 2.1
Name: librarysystem533
Version: 0.0.1
Summary: An example package
Author-email: "Kohsin Chen, YihPeng Kuo" <erin92012@gmail.com>
Classifier: Programming Language :: Python :: 3
Classifier: License :: OSI Approved :: MIT License
Classifier: Operating System :: OS Independent
Requires-Python: >=3.8
License-File: LICENSE.txt
